{"cameraMode":{"drawMode":0,"name":"Shaded","section":"Shading Mode"},"sceneLighting":true,"audioPlay":false,"sceneViewState":{"m_AlwaysRefresh":false,"showFog":true,"showSkybox":true,"showFlares":true,"showImageEffects":true,"showParticleSystems":true,"showVisualEffectGraphs":true,"m_FxEnabled":true},"in2DMode":false,"pivot":{"x":-79.59823608398438,"y":41.3112678527832,"z":246.67237854003907},"rotation":{"x":-0.2081916183233261,"y":-0.268473356962204,"z":0.05532388016581535,"w":-0.9399609565734863},"size":83.96234130859375,"orthographic":false}